{
  "id": "2026-07-17-026",
  "source_id": "https://mp.weixin.qq.com/s?__biz=MzI2NDU4OTExOQ==&mid=2247696407&idx=1&sn=99394049f6a8ab40966f9116cf56c0e2",
  "title": "一文讲透Skill",
  "source": "rss-6cec2c211479a5502896375860009782cf10c2ba",
  "url": "https://mp.weixin.qq.com/s?__biz=MzI2NDU4OTExOQ==&mid=2247696407&idx=1&sn=99394049f6a8ab40966f9116cf56c0e2",
  "summary": "该项目深入解析了‘Skill’（技能）的概念，从定义、分类、习得路径到应用场景进行系统性阐述。内容涵盖硬技能与软技能的区分、技能树构建方法、刻意练习原则，以及如何在个人成长与职场中高效积累与变现技能。旨在帮助读者建立对技能的全面认知，并掌握可操作的提升策略。",
  "tags": [
    "技能",
    "个人成长",
    "学习方法",
    "职场发展",
    "刻意练习"
  ],
  "relevance_score": 0.75,
  "category": "个人成长与学习",
  "key_insight": "技能的习得本质是系统化刻意练习与知识内化的过程，而非简单的经验积累。"
}